poshpy/__init__.py
poshpy/api.py
poshpy/models.py
poshpy-0.1.0.dist-info/LICENSE
poshpy-0.1.0.dist-info/WHEEL
poshpy-0.1.0.dist-info/METADATA
poshpy-0.1.0.dist-info/RECORD
