Metadata-Version: 2.1
Name: poshpy
Version: 0.1.0
Summary: Top-level package for poshpy.
Home-page: https://github.com/blueghostlabs/poshpy
License: Apache-2.0
Author: Jamie Phillips
Author-email: jamie@blueghostlabs.com
Requires-Python: >=3.7
Classifier: Development Status :: 2 - Pre-Alpha
Classifier: Intended Audience :: Developers
Classifier: License :: OSI Approved :: Apache Software License
Classifier: Natural Language :: English
Classifier: Programming Language :: Python :: 3
Classifier: Programming Language :: Python :: 3.7
Classifier: Programming Language :: Python :: 3.8
Classifier: Programming Language :: Python :: 3.9
